opusfilter/__init__.py
opusfilter/autogen.py
opusfilter/autogen_cluster.py
opusfilter/classifier.py
opusfilter/embeddings.py
opusfilter/filters.py
opusfilter/lid.py
opusfilter/lm.py
opusfilter/opusfilter.py
opusfilter/pipeline.py
opusfilter/preprocessors.py
opusfilter/segment_hash.py
opusfilter/subwords.py
opusfilter/tokenization.py
opusfilter/util.py
opusfilter/word_alignment.py
opusfilter-3.3.0.data/scripts/opusfilter
opusfilter-3.3.0.data/scripts/opusfilter-autogen
opusfilter-3.3.0.data/scripts/opusfilter-cmd
opusfilter-3.3.0.data/scripts/opusfilter-diagram
opusfilter-3.3.0.data/scripts/opusfilter-duplicates
opusfilter-3.3.0.data/scripts/opusfilter-scores
opusfilter-3.3.0.data/scripts/opusfilter-test
opusfilter-3.3.0.dist-info/LICENSE
opusfilter-3.3.0.dist-info/METADATA
opusfilter-3.3.0.dist-info/WHEEL
opusfilter-3.3.0.dist-info/top_level.txt
opusfilter-3.3.0.dist-info/RECORD
