Metadata-Version: 2.1
Name: opusfilter
Version: 3.3.0
Summary: Toolbox for filtering parallel corpora
Home-page: https://github.com/Helsinki-NLP/OpusFilter
Author: Mikko Aulamo, Sami Virpioja
Author-email: mikko.aulamo@helsinki.fi
Classifier: Programming Language :: Python :: 3
Classifier: License :: OSI Approved :: MIT License
Classifier: Operating System :: OS Independent
Requires-Python: >=3.8
License-File: LICENSE
Requires-Dist: setuptools
Requires-Dist: opustools>=1.6.2
Requires-Dist: beautifulsoup4>=4.8.0
Requires-Dist: graphviz
Requires-Dist: py3langid>=0.2.2
Requires-Dist: matplotlib
Requires-Dist: morfessor
Requires-Dist: pandas>=1.0.0
Requires-Dist: xxhash>=3.2.0
Requires-Dist: sentence-splitter
Requires-Dist: rapidfuzz
Requires-Dist: ruamel.yaml>=0.15.0
Requires-Dist: regex
Requires-Dist: requests
Requires-Dist: scikit-learn
Requires-Dist: subword-nmt
Requires-Dist: tqdm
Requires-Dist: iso639-lang
Requires-Dist: lingua-language-detector<2.1,>=1.3.0; python_version < "3.10"
Requires-Dist: opus-fast-mosestokenizer==0.0.8.7; python_version < "3.9"
Requires-Dist: lingua-language-detector>=2.1.1; python_version >= "3.10"
Requires-Dist: opus-fast-mosestokenizer>=0.0.8.7; python_version >= "3.9"
Provides-Extra: all
Requires-Dist: eflomal>=2.0.0; extra == "all"
Requires-Dist: jieba>=0.42; extra == "all"
Requires-Dist: mecab-python3>=1.0.8; extra == "all"
Requires-Dist: unidic-lite; extra == "all"
Requires-Dist: laserembeddings; extra == "all"
Requires-Dist: varikn; extra == "all"
Requires-Dist: pytest; extra == "all"
Requires-Dist: myst-parser; extra == "all"
Requires-Dist: sphinx; extra == "all"
Requires-Dist: sphinx-rtd-theme; extra == "all"
Requires-Dist: sphinxcontrib-bibtex; extra == "all"
Provides-Extra: docs
Requires-Dist: myst-parser; extra == "docs"
Requires-Dist: sphinx; extra == "docs"
Requires-Dist: sphinx-rtd-theme; extra == "docs"
Requires-Dist: sphinxcontrib-bibtex; extra == "docs"
Provides-Extra: eflomal
Requires-Dist: eflomal>=2.0.0; extra == "eflomal"
Provides-Extra: fasttext
Requires-Dist: py3langid<0.3.0; extra == "fasttext"
Requires-Dist: numpy<2.0.0; extra == "fasttext"
Requires-Dist: fasttext; extra == "fasttext"
Provides-Extra: heliport
Requires-Dist: heliport>=0.10.0; extra == "heliport"
Provides-Extra: jieba
Requires-Dist: jieba>=0.42; extra == "jieba"
Provides-Extra: laser
Requires-Dist: laserembeddings; extra == "laser"
Provides-Extra: mecab
Requires-Dist: mecab-python3>=1.0.8; extra == "mecab"
Requires-Dist: unidic-lite; extra == "mecab"
Provides-Extra: pycld2
Requires-Dist: pycld2; extra == "pycld2"
Provides-Extra: test
Requires-Dist: pytest; extra == "test"
Provides-Extra: varikn
Requires-Dist: varikn; extra == "varikn"
